kitch.numerical-0.0.2.dist-info/DESCRIPTION.rst
kitch.numerical-0.0.2.dist-info/METADATA
kitch.numerical-0.0.2.dist-info/RECORD
kitch.numerical-0.0.2.dist-info/WHEEL
kitch.numerical-0.0.2.dist-info/metadata.json
kitch.numerical-0.0.2.dist-info/top_level.txt
numerical/__init__.py
numerical/conversions.py
numerical/decorators.py
numerical/functions.py
numerical/predicates.py
numerical/strategies.py
